[
  {
    "id": "c584fd02-977f-46c6-801b-8392b01fe2b3",
    "firstName":"Marcus",
    "lastName":"Campbell",
    "email":"mcampbell@email.com",
    "password": "asdfasdf",
    "phoneNum": "8035652570",
    "street": "814 Cookie St",
    "town": "Columbia",
    "state": "SC",
    "zipCode" : 29201,
    "country": "USA",
    "birthday":"April 15, 1984",
    "director": true
  },
  {
    "id": "27f4c71b-743d-4ffa-8b31-cb3fa1dd063c",
    "firstName":"Tyree",
    "lastName":"Hum",
    "email":"thum@email.com",
    "password": "asdf1234",
    "phoneNum": "8034545770",
    "street": "815 Cookie St",
    "town": "Columbia",
    "state": "SC",
    "zipCode" : 29201,
    "country": "USA",
    "birthday":"April 16, 1974",
    "director": true
  },
  {
    "id": "eb976e86-5667-4ff6-9822-9da64d217558",
    "firstName":"Aiyanna",
    "lastName":"Blair",
    "email":"AiyannaBlair@email.com",
    "password": "AiyannaIsCool",
    "phoneNum": "8037894561",
    "street": "316 joker St",
    "town": "Columbia",
    "state": "SC",
    "zipCode" : 29201,
    "country": "USA",
    "birthday":"March 27, 1984",
    "director": true
  }
]